{
    "go-enum": {
        "cargoLocks": null,
        "date": null,
        "extract": null,
        "name": "go-enum",
        "passthru": null,
        "pinned": false,
        "src": {
            "deepClone": false,
            "fetchSubmodules": false,
            "leaveDotGit": false,
            "name": null,
            "owner": "abice",
            "repo": "go-enum",
            "rev": "v0.6.0",
            "sha256": "sha256-Mt45Qz8l++bvBLKEpbX0m8iTkHDpsZtdYhhHUprQKY8=",
            "type": "github"
        },
        "version": "v0.6.0"
    },
    "gomvp": {
        "cargoLocks": null,
        "date": "2022-10-25",
        "extract": null,
        "name": "gomvp",
        "passthru": null,
        "pinned": false,
        "src": {
            "deepClone": false,
            "fetchSubmodules": false,
            "leaveDotGit": false,
            "name": null,
            "owner": "abenz1267",
            "repo": "gomvp",
            "rev": "5b06c041c898822fd72cd245188e51d112adae74",
            "sha256": "sha256-dXjI+nItJCAGKxyC9tX11hxWHCP+NgXtTYtm5+6dqDU=",
            "type": "github"
        },
        "version": "5b06c041c898822fd72cd245188e51d112adae74"
    },
    "helm-ls": {
        "cargoLocks": null,
        "date": null,
        "extract": null,
        "name": "helm-ls",
        "passthru": null,
        "pinned": false,
        "src": {
            "deepClone": false,
            "fetchSubmodules": false,
            "leaveDotGit": false,
            "name": null,
            "owner": "mrjosh",
            "repo": "helm-ls",
            "rev": "v0.0.8",
            "sha256": "sha256-q9RK7wTEbwptzNrXzifq6vUpOKD3idsG5FZKpQZ1uCc=",
            "type": "github"
        },
        "version": "v0.0.8"
    },
    "jq-lsp": {
        "cargoLocks": null,
        "date": "2024-01-01",
        "extract": null,
        "name": "jq-lsp",
        "passthru": null,
        "pinned": false,
        "src": {
            "deepClone": false,
            "fetchSubmodules": false,
            "leaveDotGit": false,
            "name": null,
            "owner": "wader",
            "repo": "jq-lsp",
            "rev": "80c097c71b141dd07a17741bbd94ec28842d124e",
            "sha256": "sha256-i/VnFtQ02TtVtGJd7w9uYOsTRLYwReX7aqxFHKBU6io=",
            "type": "github"
        },
        "version": "80c097c71b141dd07a17741bbd94ec28842d124e"
    },
    "json-to-struct": {
        "cargoLocks": null,
        "date": "2023-06-13",
        "extract": null,
        "name": "json-to-struct",
        "passthru": null,
        "pinned": false,
        "src": {
            "deepClone": false,
            "fetchSubmodules": false,
            "leaveDotGit": false,
            "name": null,
            "owner": "tmc",
            "repo": "json-to-struct",
            "rev": "1f65fffbfdbb2b0e56a3f6f6cd24daad58e90dec",
            "sha256": "sha256-l/XLZstZFVnYXRqtng1oiCSvhNAomyeTuI1OtCb8UHo=",
            "type": "github"
        },
        "version": "1f65fffbfdbb2b0e56a3f6f6cd24daad58e90dec"
    }
}